senaite.impress-1.2.1-py2.7-nspkg.pth
senaite/impress/__init__.py
senaite/impress/ajax.py
senaite/impress/config.py
senaite/impress/configure.zcml
senaite/impress/controlpanel.py
senaite/impress/decorators.py
senaite/impress/exceptions.py
senaite/impress/interfaces.py
senaite/impress/javascripts.py
senaite/impress/publisher.py
senaite/impress/publishview.py
senaite/impress/reportview.py
senaite/impress/setuphandlers.py
senaite/impress/storage.py
senaite/impress/template.py
senaite/impress/vocabularies.py
senaite/impress/analysisrequest/__init__.py
senaite/impress/analysisrequest/configure.zcml
senaite/impress/analysisrequest/model.py
senaite/impress/analysisrequest/reportview.py
senaite/impress/locales/de/LC_MESSAGES/senaite.impress.po
senaite/impress/locales/en/LC_MESSAGES/senaite.impress.po
senaite/impress/locales/es/LC_MESSAGES/senaite.impress.po
senaite/impress/locales/hu/LC_MESSAGES/senaite.impress.po
senaite/impress/locales/lo_LA/LC_MESSAGES/senaite.impress.po
senaite/impress/locales/zh_CN/LC_MESSAGES/senaite.impress.po
senaite/impress/profiles/default/actionicons.xml
senaite/impress/profiles/default/browserlayer.xml
senaite/impress/profiles/default/controlpanel.xml
senaite/impress/profiles/default/metadata.xml
senaite/impress/profiles/default/registry.xml
senaite/impress/profiles/default/senaite.impress.install.txt
senaite/impress/profiles/uninstall/browserlayer.xml
senaite/impress/profiles/uninstall/metadata.xml
senaite/impress/profiles/uninstall/registry.xml
senaite/impress/profiles/uninstall/senaite.impress.uninstall.txt
senaite/impress/static/.DS_Store
senaite/impress/static/css/bootstrap-print.css
senaite/impress/static/css/bootstrap.min.css
senaite/impress/static/css/fontawesome-all.min.css
senaite/impress/static/css/print.css
senaite/impress/static/img/icon.png
senaite/impress/static/js/README.md
senaite/impress/static/js/yarn.lock
senaite/impress/static/js/scripts/bootstrap.bundle.min.js
senaite/impress/static/js/scripts/senaite.impress.publish.js
senaite.impress-1.2.1.dist-info/LICENSE
senaite.impress-1.2.1.dist-info/METADATA
senaite.impress-1.2.1.dist-info/WHEEL
senaite.impress-1.2.1.dist-info/entry_points.txt
senaite.impress-1.2.1.dist-info/namespace_packages.txt
senaite.impress-1.2.1.dist-info/top_level.txt
senaite.impress-1.2.1.dist-info/RECORD
