Metadata-Version: 2.1
Name: senaite.impress
Version: 1.2.1
Summary: Publication of HTML/PDF Reports in SENAITE
Home-page: https://github.com/senaite/senaite.impress
Author: SENAITE Foundation
Author-email: hello@senaite.com
License: GPLv2
Platform: UNKNOWN
Classifier: Framework :: Plone
Classifier: Framework :: Zope2
Classifier: Programming Language :: Python
Classifier: Development Status :: 5 - Production/Stable
Classifier: License :: OSI Approved :: GNU General Public License v2 (GPLv2)
Requires-Dist: setuptools
Requires-Dist: senaite.lims (>=1.3.0)
Requires-Dist: beautifulsoup4
Requires-Dist: cairocffi (<1.0.0)
Requires-Dist: CairoSVG (==1.0.20)
Requires-Dist: WeasyPrint (==0.42.3)
Requires-Dist: tinycss2 (<1.0.0)
Provides-Extra: test
Requires-Dist: Products.PloneTestCase ; extra == 'test'
Requires-Dist: Products.SecureMailHost ; extra == 'test'
Requires-Dist: plone.app.testing ; extra == 'test'
Requires-Dist: unittest2 ; extra == 'test'
